{
      "activity": {
        "properties": {
          "_metadata": {
            "properties": {
              "id": {
                "type": "string"
              },
              "index": {
                "type": "string"
              },
              "type": {
                "type": "string"
              }
            }
          },
          "actor": {
            "properties": {
              "displayName": {
                "type": "string"
              },
              "extensions": {
                "properties": {
                  "favorites": {
                    "type": "long"
                  },
                  "followers": {
                    "type": "long"
                  },
                  "location": {
                    "type": "string"
                  },
                  "posts": {
                    "type": "long"
                  },
                  "screenName": {
                    "type": "string"
                  }
                }
              },
              "handle": {
                "type": "string"
              },
              "id": {
                "type": "string"
              },
              "image": {
                "properties": {
                  "url": {
                    "type": "string"
                  }
                }
              },
              "objectType": {
                "type": "string"
              },
              "summary": {
                "type": "string"
              },
              "url": {
                "type": "string"
              }
            }
          },
          "content": {
            "type": "string"
          },
          "extensions": {
            "properties": {
              "alchemykeywords": {
                "properties": {
                  "keywords": {
                    "properties": {
                      "relevance": {
                        "type": "string"
                      },
                      "sentiment": {
                        "properties": {
                          "mixed": {
                            "type": "long"
                          },
                          "score": {
                            "type": "double"
                          },
                          "type": {
                            "type": "string"
                          }
                        }
                      },
                      "text": {
                        "type": "string"
                      }
                    }
                  },
                  "language": {
                    "type": "string"
                  },
                  "status": {
                    "type": "string"
                  },
                  "statusInfo": {
                    "type": "string"
                  },
                  "statusMessage": {
                    "type": "string"
                  },
                  "text": {
                    "type": "string"
                  },
                  "totalTransactions": {
                    "type": "string"
                  },
                  "url": {
                    "type": "string"
                  },
                  "usage": {
                    "type": "string"
                  },
                  "warningMessage": {
                    "type": "string"
                  }
                }
              },
              "entities": {
                "properties": {
                  "entities": {
                    "properties": {
                      "count": {
                        "type": "long"
                      },
                      "disambiguated": {
                        "properties": {
                          "census": {
                            "type": "string"
                          },
                          "ciaFactbook": {
                            "type": "string"
                          },
                          "crunchbase": {
                            "type": "string"
                          },
                          "dbpedia": {
                            "type": "string"
                          },
                          "freebase": {
                            "type": "string"
                          },
                          "geo": {
                            "type": "string"
                          },
                          "geonames": {
                            "type": "string"
                          },
                          "musicBrainz": {
                            "type": "string"
                          },
                          "name": {
                            "type": "string"
                          },
                          "opencyc": {
                            "type": "string"
                          },
                          "subType": {
                            "type": "string"
                          },
                          "website": {
                            "type": "string"
                          },
                          "yago": {
                            "type": "string"
                          }
                        }
                      },
                      "knowledgeGraph": {
                        "properties": {
                          "typeHierarchy": {
                            "type": "string"
                          }
                        }
                      },
                      "relevance": {
                        "type": "string"
                      },
                      "sentiment": {
                        "properties": {
                          "mixed": {
                            "type": "long"
                          },
                          "score": {
                            "type": "double"
                          },
                          "type": {
                            "type": "string"
                          }
                        }
                      },
                      "text": {
                        "type": "string"
                      },
                      "type": {
                        "type": "string"
                      }
                    }
                  },
                  "language": {
                    "type": "string"
                  },
                  "status": {
                    "type": "string"
                  },
                  "statusInfo": {
                    "type": "string"
                  },
                  "statusMessage": {
                    "type": "string"
                  },
                  "totalTransactions": {
                    "type": "long"
                  },
                  "url": {
                    "type": "string"
                  },
                  "usage": {
                    "type": "string"
                  },
                  "warningMessage": {
                    "type": "string"
                  }
                }
              },
              "hashtags": {
                "type": "string"
              },
              "keywords": {
                "type": "string"
              },
              "likes": {
                "properties": {
                  "count": {
                    "type": "long"
                  },
                  "perspectival": {
                    "type": "boolean"
                  }
                }
              },
              "location": {
                "properties": {
                  "coordinates": {
                    "properties": {
                      "coordinates": {
                        "type": "double"
                      },
                      "type": {
                        "type": "string"
                      }
                    }
                  },
                  "id": {
                    "type": "string"
                  }
                }
              },
              "rebroadcasts": {
                "properties": {
                  "count": {
                    "type": "long"
                  },
                  "perspectival": {
                    "type": "boolean"
                  }
                }
              },
              "sentiment": {
                "properties": {
                  "docSentiment": {
                    "properties": {
                      "mixed": {
                        "type": "long"
                      },
                      "score": {
                        "type": "double"
                      },
                      "type": {
                        "type": "string"
                      }
                    }
                  },
                  "language": {
                    "type": "string"
                  },
                  "status": {
                    "type": "string"
                  },
                  "statusInfo": {
                    "type": "string"
                  },
                  "statusMessage": {
                    "type": "string"
                  },
                  "text": {
                    "type": "string"
                  },
                  "totalTransactions": {
                    "type": "long"
                  },
                  "url": {
                    "type": "string"
                  },
                  "usage": {
                    "type": "string"
                  },
                  "warningMessage": {
                    "type": "string"
                  }
                }
              },
              "taxonomy": {
                "properties": {
                  "language": {
                    "type": "string"
                  },
                  "status": {
                    "type": "string"
                  },
                  "statusInfo": {
                    "type": "string"
                  },
                  "statusMessage": {
                    "type": "string"
                  },
                  "taxonomy": {
                    "properties": {
                      "confident": {
                        "type": "boolean"
                      },
                      "label": {
                        "type": "string"
                      },
                      "score": {
                        "type": "double"
                      }
                    }
                  },
                  "text": {
                    "type": "string"
                  },
                  "totalTransactions": {
                    "type": "long"
                  },
                  "url": {
                    "type": "string"
                  },
                  "usage": {
                    "type": "string"
                  },
                  "warningMessage": {
                    "type": "string"
                  }
                }
              },
              "twitter": {
                "properties": {
                  "coordinates": {
                    "properties": {
                      "coordinates": {
                        "type": "double"
                      },
                      "type": {
                        "type": "string"
                      }
                    }
                  },
                  "created_at": {
                    "type": "date",
                    "format": "dateOptionalTime"
                  },
                  "current_user_retweet": {
                    "properties": {
                      "id": {
                        "type": "long"
                      },
                      "id_str": {
                        "type": "string"
                      }
                    }
                  },
                  "entities": {
                    "properties": {
                      "hashtags": {
                        "properties": {
                          "indices": {
                            "type": "long"
                          },
                          "text": {
                            "type": "string"
                          }
                        }
                      },
                      "media": {
                        "properties": {
                          "display_url": {
                            "type": "string"
                          },
                          "expanded_url": {
                            "type": "string"
                          },
                          "id": {
                            "type": "long"
                          },
                          "id_str": {
                            "type": "string"
                          },
                          "indices": {
                            "type": "long"
                          },
                          "media_url": {
                            "type": "string"
                          },
                          "media_url_https": {
                            "type": "string"
                          },
                          "sizes": {
                            "properties": {
                              "large": {
                                "properties": {
                                  "h": {
                                    "type": "long"
                                  },
                                  "resize": {
                                    "type": "string"
                                  },
                                  "w": {
                                    "type": "long"
                                  }
                                }
                              },
                              "medium": {
                                "properties": {
                                  "h": {
                                    "type": "long"
                                  },
                                  "resize": {
                                    "type": "string"
                                  },
                                  "w": {
                                    "type": "long"
                                  }
                                }
                              },
                              "small": {
                                "properties": {
                                  "h": {
                                    "type": "long"
                                  },
                                  "resize": {
                                    "type": "string"
                                  },
                                  "w": {
                                    "type": "long"
                                  }
                                }
                              },
                              "thumb": {
                                "properties": {
                                  "h": {
                                    "type": "long"
                                  },
                                  "resize": {
                                    "type": "string"
                                  },
                                  "w": {
                                    "type": "long"
                                  }
                                }
                              }
                            }
                          },
                          "source_status_id": {
                            "type": "long"
                          },
                          "source_status_id_str": {
                            "type": "string"
                          },
                          "source_user_id": {
                            "type": "long"
                          },
                          "source_user_id_str": {
                            "type": "string"
                          },
                          "type": {
                            "type": "string"
                          },
                          "url": {
                            "type": "string"
                          }
                        }
                      },
                      "symbols": {
                        "properties": {
                          "indices": {
                            "type": "long"
                          },
                          "text": {
                            "type": "string"
                          }
                        }
                      },
                      "urls": {
                        "properties": {
                          "display_url": {
                            "type": "string"
                          },
                          "expanded_url": {
                            "type": "string"
                          },
                          "indices": {
                            "type": "long"
                          },
                          "url": {
                            "type": "string"
                          }
                        }
                      },
                      "user_mentions": {
                        "properties": {
                          "id": {
                            "type": "long"
                          },
                          "id_str": {
                            "type": "string"
                          },
                          "indices": {
                            "type": "long"
                          },
                          "name": {
                            "type": "string"
                          },
                          "screen_name": {
                            "type": "string"
                          }
                        }
                      }
                    }
                  },
                  "extended_entities": {
                    "properties": {
                      "media": {
                        "properties": {
                          "display_url": {
                            "type": "string"
                          },
                          "expanded_url": {
                            "type": "string"
                          },
                          "id": {
                            "type": "long"
                          },
                          "id_str": {
                            "type": "string"
                          },
                          "indices": {
                            "type": "long"
                          },
                          "media_url": {
                            "type": "string"
                          },
                          "media_url_https": {
                            "type": "string"
                          },
                          "sizes": {
                            "properties": {
                              "large": {
                                "properties": {
                                  "h": {
                                    "type": "long"
                                  },
                                  "resize": {
                                    "type": "string"
                                  },
                                  "w": {
                                    "type": "long"
                                  }
                                }
                              },
                              "medium": {
                                "properties": {
                                  "h": {
                                    "type": "long"
                                  },
                                  "resize": {
                                    "type": "string"
                                  },
                                  "w": {
                                    "type": "long"
                                  }
                                }
                              },
                              "small": {
                                "properties": {
                                  "h": {
                                    "type": "long"
                                  },
                                  "resize": {
                                    "type": "string"
                                  },
                                  "w": {
                                    "type": "long"
                                  }
                                }
                              },
                              "thumb": {
                                "properties": {
                                  "h": {
                                    "type": "long"
                                  },
                                  "resize": {
                                    "type": "string"
                                  },
                                  "w": {
                                    "type": "long"
                                  }
                                }
                              }
                            }
                          },
                          "source_status_id": {
                            "type": "long"
                          },
                          "source_status_id_str": {
                            "type": "string"
                          },
                          "source_user_id": {
                            "type": "long"
                          },
                          "source_user_id_str": {
                            "type": "string"
                          },
                          "type": {
                            "type": "string"
                          },
                          "url": {
                            "type": "string"
                          },
                          "video_info": {
                            "properties": {
                              "aspect_ratio": {
                                "type": "long"
                              },
                              "duration_millis": {
                                "type": "long"
                              },
                              "variants": {
                                "properties": {
                                  "bitrate": {
                                    "type": "long"
                                  },
                                  "content_type": {
                                    "type": "string"
                                  },
                                  "url": {
                                    "type": "string"
                                  }
                                }
                              }
                            }
                          }
                        }
                      }
                    }
                  },
                  "favorite_count": {
                    "type": "long"
                  },
                  "favorited": {
                    "type": "boolean"
                  },
                  "geo": {
                    "properties": {
                      "coordinates": {
                        "type": "double"
                      },
                      "type": {
                        "type": "string"
                      }
                    }
                  },
                  "id": {
                    "type": "long"
                  },
                  "id_str": {
                    "type": "string"
                  },
                  "in_reply_to_screen_name": {
                    "type": "string"
                  },
                  "in_reply_to_status_id": {
                    "type": "long"
                  },
                  "in_reply_to_status_id_str": {
                    "type": "string"
                  },
                  "in_reply_to_user_id": {
                    "type": "long"
                  },
                  "in_reply_to_user_id_str": {
                    "type": "string"
                  },
                  "lang": {
                    "type": "string"
                  },
                  "place": {
                    "properties": {
                      "attributes": {
                        "type": "object"
                      },
                      "bounding_box": {
                        "properties": {
                          "coordinates": {
                            "type": "double"
                          },
                          "type": {
                            "type": "string"
                          }
                        }
                      },
                      "country": {
                        "type": "string"
                      },
                      "country_code": {
                        "type": "string"
                      },
                      "full_name": {
                        "type": "string"
                      },
                      "id": {
                        "type": "string"
                      },
                      "name": {
                        "type": "string"
                      },
                      "place_type": {
                        "type": "string"
                      },
                      "url": {
                        "type": "string"
                      }
                    }
                  },
                  "possibly_sensitive": {
                    "type": "boolean"
                  },
                  "retweet_count": {
                    "type": "long"
                  },
                  "retweeted": {
                    "type": "boolean"
                  },
                  "retweeted_status": {
                    "properties": {
                      "coordinates": {
                        "properties": {
                          "coordinates": {
                            "type": "double"
                          },
                          "type": {
                            "type": "string"
                          }
                        }
                      },
                      "created_at": {
                        "type": "date",
                        "format": "dateOptionalTime"
                      },
                      "entities": {
                        "properties": {
                          "hashtags": {
                            "properties": {
                              "indices": {
                                "type": "long"
                              },
                              "text": {
                                "type": "string"
                              }
                            }
                          },
                          "media": {
                            "properties": {
                              "display_url": {
                                "type": "string"
                              },
                              "expanded_url": {
                                "type": "string"
                              },
                              "id": {
                                "type": "long"
                              },
                              "id_str": {
                                "type": "string"
                              },
                              "indices": {
                                "type": "long"
                              },
                              "media_url": {
                                "type": "string"
                              },
                              "media_url_https": {
                                "type": "string"
                              },
                              "sizes": {
                                "properties": {
                                  "large": {
                                    "properties": {
                                      "h": {
                                        "type": "long"
                                      },
                                      "resize": {
                                        "type": "string"
                                      },
                                      "w": {
                                        "type": "long"
                                      }
                                    }
                                  },
                                  "medium": {
                                    "properties": {
                                      "h": {
                                        "type": "long"
                                      },
                                      "resize": {
                                        "type": "string"
                                      },
                                      "w": {
                                        "type": "long"
                                      }
                                    }
                                  },
                                  "small": {
                                    "properties": {
                                      "h": {
                                        "type": "long"
                                      },
                                      "resize": {
                                        "type": "string"
                                      },
                                      "w": {
                                        "type": "long"
                                      }
                                    }
                                  },
                                  "thumb": {
                                    "properties": {
                                      "h": {
                                        "type": "long"
                                      },
                                      "resize": {
                                        "type": "string"
                                      },
                                      "w": {
                                        "type": "long"
                                      }
                                    }
                                  }
                                }
                              },
                              "source_status_id": {
                                "type": "long"
                              },
                              "source_status_id_str": {
                                "type": "string"
                              },
                              "source_user_id": {
                                "type": "long"
                              },
                              "source_user_id_str": {
                                "type": "string"
                              },
                              "type": {
                                "type": "string"
                              },
                              "url": {
                                "type": "string"
                              }
                            }
                          },
                          "symbols": {
                            "properties": {
                              "indices": {
                                "type": "long"
                              },
                              "text": {
                                "type": "string"
                              }
                            }
                          },
                          "urls": {
                            "properties": {
                              "display_url": {
                                "type": "string"
                              },
                              "expanded_url": {
                                "type": "string"
                              },
                              "indices": {
                                "type": "long"
                              },
                              "url": {
                                "type": "string"
                              }
                            }
                          },
                          "user_mentions": {
                            "properties": {
                              "id": {
                                "type": "long"
                              },
                              "id_str": {
                                "type": "string"
                              },
                              "indices": {
                                "type": "long"
                              },
                              "name": {
                                "type": "string"
                              },
                              "screen_name": {
                                "type": "string"
                              }
                            }
                          }
                        }
                      },
                      "extended_entities": {
                        "properties": {
                          "media": {
                            "properties": {
                              "display_url": {
                                "type": "string"
                              },
                              "expanded_url": {
                                "type": "string"
                              },
                              "id": {
                                "type": "long"
                              },
                              "id_str": {
                                "type": "string"
                              },
                              "indices": {
                                "type": "long"
                              },
                              "media_url": {
                                "type": "string"
                              },
                              "media_url_https": {
                                "type": "string"
                              },
                              "sizes": {
                                "properties": {
                                  "large": {
                                    "properties": {
                                      "h": {
                                        "type": "long"
                                      },
                                      "resize": {
                                        "type": "string"
                                      },
                                      "w": {
                                        "type": "long"
                                      }
                                    }
                                  },
                                  "medium": {
                                    "properties": {
                                      "h": {
                                        "type": "long"
                                      },
                                      "resize": {
                                        "type": "string"
                                      },
                                      "w": {
                                        "type": "long"
                                      }
                                    }
                                  },
                                  "small": {
                                    "properties": {
                                      "h": {
                                        "type": "long"
                                      },
                                      "resize": {
                                        "type": "string"
                                      },
                                      "w": {
                                        "type": "long"
                                      }
                                    }
                                  },
                                  "thumb": {
                                    "properties": {
                                      "h": {
                                        "type": "long"
                                      },
                                      "resize": {
                                        "type": "string"
                                      },
                                      "w": {
                                        "type": "long"
                                      }
                                    }
                                  }
                                }
                              },
                              "source_status_id": {
                                "type": "long"
                              },
                              "source_status_id_str": {
                                "type": "string"
                              },
                              "source_user_id": {
                                "type": "long"
                              },
                              "source_user_id_str": {
                                "type": "string"
                              },
                              "type": {
                                "type": "string"
                              },
                              "url": {
                                "type": "string"
                              },
                              "video_info": {
                                "properties": {
                                  "aspect_ratio": {
                                    "type": "long"
                                  },
                                  "duration_millis": {
                                    "type": "long"
                                  },
                                  "variants": {
                                    "properties": {
                                      "bitrate": {
                                        "type": "long"
                                      },
                                      "content_type": {
                                        "type": "string"
                                      },
                                      "url": {
                                        "type": "string"
                                      }
                                    }
                                  }
                                }
                              }
                            }
                          }
                        }
                      },
                      "favorite_count": {
                        "type": "long"
                      },
                      "favorited": {
                        "type": "boolean"
                      },
                      "geo": {
                        "properties": {
                          "coordinates": {
                            "type": "double"
                          },
                          "type": {
                            "type": "string"
                          }
                        }
                      },
                      "id": {
                        "type": "long"
                      },
                      "id_str": {
                        "type": "string"
                      },
                      "in_reply_to_screen_name": {
                        "type": "string"
                      },
                      "in_reply_to_status_id": {
                        "type": "long"
                      },
                      "in_reply_to_status_id_str": {
                        "type": "string"
                      },
                      "in_reply_to_user_id": {
                        "type": "long"
                      },
                      "in_reply_to_user_id_str": {
                        "type": "string"
                      },
                      "lang": {
                        "type": "string"
                      },
                      "place": {
                        "properties": {
                          "attributes": {
                            "properties": {
                              "street_address": {
                                "type": "string"
                              }
                            }
                          },
                          "bounding_box": {
                            "properties": {
                              "coordinates": {
                                "type": "double"
                              },
                              "type": {
                                "type": "string"
                              }
                            }
                          },
                          "country": {
                            "type": "string"
                          },
                          "country_code": {
                            "type": "string"
                          },
                          "full_name": {
                            "type": "string"
                          },
                          "id": {
                            "type": "string"
                          },
                          "name": {
                            "type": "string"
                          },
                          "place_type": {
                            "type": "string"
                          },
                          "url": {
                            "type": "string"
                          }
                        }
                      },
                      "possibly_sensitive": {
                        "type": "boolean"
                      },
                      "retweet_count": {
                        "type": "long"
                      },
                      "retweeted": {
                        "type": "boolean"
                      },
                      "scopes": {
                        "properties": {
                          "followers": {
                            "type": "boolean"
                          },
                          "place_ids": {
                            "type": "string"
                          }
                        }
                      },
                      "source": {
                        "type": "string"
                      },
                      "text": {
                        "type": "string"
                      },
                      "truncated": {
                        "type": "boolean"
                      },
                      "user": {
                        "properties": {
                          "contributors_enabled": {
                            "type": "boolean"
                          },
                          "created_at": {
                            "type": "date",
                            "format": "dateOptionalTime"
                          },
                          "default_profile": {
                            "type": "boolean"
                          },
                          "default_profile_image": {
                            "type": "boolean"
                          },
                          "description": {
                            "type": "string"
                          },
                          "entities": {
                            "properties": {
                              "description": {
                                "properties": {
                                  "urls": {
                                    "properties": {
                                      "display_url": {
                                        "type": "string"
                                      },
                                      "expanded_url": {
                                        "type": "string"
                                      },
                                      "indices": {
                                        "type": "long"
                                      },
                                      "url": {
                                        "type": "string"
                                      }
                                    }
                                  }
                                }
                              },
                              "url": {
                                "properties": {
                                  "urls": {
                                    "properties": {
                                      "display_url": {
                                        "type": "string"
                                      },
                                      "expanded_url": {
                                        "type": "string"
                                      },
                                      "indices": {
                                        "type": "long"
                                      },
                                      "url": {
                                        "type": "string"
                                      }
                                    }
                                  }
                                }
                              }
                            }
                          },
                          "favourites_count": {
                            "type": "long"
                          },
                          "follow_request_sent": {
                            "type": "boolean"
                          },
                          "followers_count": {
                            "type": "long"
                          },
                          "following": {
                            "type": "boolean"
                          },
                          "friends_count": {
                            "type": "long"
                          },
                          "geo_enabled": {
                            "type": "boolean"
                          },
                          "id": {
                            "type": "long"
                          },
                          "id_str": {
                            "type": "string"
                          },
                          "is_translation_enabled": {
                            "type": "boolean"
                          },
                          "is_translator": {
                            "type": "boolean"
                          },
                          "lang": {
                            "type": "string"
                          },
                          "listed_count": {
                            "type": "long"
                          },
                          "location": {
                            "type": "string"
                          },
                          "name": {
                            "type": "string"
                          },
                          "notifications": {
                            "type": "boolean"
                          },
                          "profile_background_color": {
                            "type": "string"
                          },
                          "profile_background_image_url": {
                            "type": "string"
                          },
                          "profile_background_image_url_https": {
                            "type": "string"
                          },
                          "profile_background_tile": {
                            "type": "boolean"
                          },
                          "profile_banner_url": {
                            "type": "string"
                          },
                          "profile_image_url": {
                            "type": "string"
                          },
                          "profile_image_url_https": {
                            "type": "string"
                          },
                          "profile_link_color": {
                            "type": "string"
                          },
                          "profile_sidebar_border_color": {
                            "type": "string"
                          },
                          "profile_sidebar_fill_color": {
                            "type": "string"
                          },
                          "profile_text_color": {
                            "type": "string"
                          },
                          "profile_use_background_image": {
                            "type": "boolean"
                          },
                          "protected": {
                            "type": "boolean"
                          },
                          "screen_name": {
                            "type": "string"
                          },
                          "statuses_count": {
                            "type": "long"
                          },
                          "time_zone": {
                            "type": "string"
                          },
                          "url": {
                            "type": "string"
                          },
                          "utc_offset": {
                            "type": "long"
                          },
                          "verified": {
                            "type": "boolean"
                          }
                        }
                      }
                    }
                  },
                  "scopes": {
                    "properties": {
                      "place_ids": {
                        "type": "string"
                      }
                    }
                  },
                  "source": {
                    "type": "string"
                  },
                  "text": {
                    "type": "string"
                  },
                  "truncated": {
                    "type": "boolean"
                  },
                  "user": {
                    "properties": {
                      "contributors_enabled": {
                        "type": "boolean"
                      },
                      "created_at": {
                        "type": "date",
                        "format": "dateOptionalTime"
                      },
                      "default_profile": {
                        "type": "boolean"
                      },
                      "default_profile_image": {
                        "type": "boolean"
                      },
                      "description": {
                        "type": "string"
                      },
                      "entities": {
                        "properties": {
                          "description": {
                            "properties": {
                              "urls": {
                                "properties": {
                                  "display_url": {
                                    "type": "string"
                                  },
                                  "expanded_url": {
                                    "type": "string"
                                  },
                                  "indices": {
                                    "type": "long"
                                  },
                                  "url": {
                                    "type": "string"
                                  }
                                }
                              }
                            }
                          },
                          "url": {
                            "properties": {
                              "urls": {
                                "properties": {
                                  "display_url": {
                                    "type": "string"
                                  },
                                  "expanded_url": {
                                    "type": "string"
                                  },
                                  "indices": {
                                    "type": "long"
                                  },
                                  "url": {
                                    "type": "string"
                                  }
                                }
                              }
                            }
                          }
                        }
                      },
                      "favourites_count": {
                        "type": "long"
                      },
                      "follow_request_sent": {
                        "type": "boolean"
                      },
                      "followers_count": {
                        "type": "long"
                      },
                      "following": {
                        "type": "boolean"
                      },
                      "friends_count": {
                        "type": "long"
                      },
                      "geo_enabled": {
                        "type": "boolean"
                      },
                      "id": {
                        "type": "long"
                      },
                      "id_str": {
                        "type": "string"
                      },
                      "is_translation_enabled": {
                        "type": "boolean"
                      },
                      "is_translator": {
                        "type": "boolean"
                      },
                      "lang": {
                        "type": "string"
                      },
                      "listed_count": {
                        "type": "long"
                      },
                      "location": {
                        "type": "string"
                      },
                      "name": {
                        "type": "string"
                      },
                      "notifications": {
                        "type": "boolean"
                      },
                      "profile_background_color": {
                        "type": "string"
                      },
                      "profile_background_image_url": {
                        "type": "string"
                      },
                      "profile_background_image_url_https": {
                        "type": "string"
                      },
                      "profile_background_tile": {
                        "type": "boolean"
                      },
                      "profile_banner_url": {
                        "type": "string"
                      },
                      "profile_image_url": {
                        "type": "string"
                      },
                      "profile_image_url_https": {
                        "type": "string"
                      },
                      "profile_link_color": {
                        "type": "string"
                      },
                      "profile_sidebar_border_color": {
                        "type": "string"
                      },
                      "profile_sidebar_fill_color": {
                        "type": "string"
                      },
                      "profile_text_color": {
                        "type": "string"
                      },
                      "profile_use_background_image": {
                        "type": "boolean"
                      },
                      "protected": {
                        "type": "boolean"
                      },
                      "screen_name": {
                        "type": "string"
                      },
                      "statuses_count": {
                        "type": "long"
                      },
                      "time_zone": {
                        "type": "string"
                      },
                      "url": {
                        "type": "string"
                      },
                      "utc_offset": {
                        "type": "long"
                      },
                      "verified": {
                        "type": "boolean"
                      }
                    }
                  }
                }
              },
              "user_mentions": {
                "properties": {
                  "displayName": {
                    "type": "string"
                  },
                  "handle": {
                    "type": "string"
                  },
                  "id": {
                    "type": "string"
                  }
                }
              }
            }
          },
          "id": {
            "type": "string"
          },
          "links": {
            "type": "string"
          },
          "object": {
            "properties": {
              "content": {
                "type": "string"
              },
              "id": {
                "type": "string"
              },
              "objectType": {
                "type": "string"
              }
            }
          },
          "provider": {
            "properties": {
              "displayName": {
                "type": "string"
              },
              "id": {
                "type": "string"
              },
              "objectType": {
                "type": "string"
              }
            }
          },
          "published": {
            "type": "date",
            "format": "dateOptionalTime"
          },
          "title": {
            "type": "string"
          },
          "url": {
            "type": "string"
          },
          "verb": {
            "type": "string"
          }
        }
      }


}